pyit2fls/__init__.py
pyit2fls/fuzzymatrix.py
pyit2fls/learning.py
pyit2fls/pyit2fls.py
pyit2fls-0.8.6.dist-info/licenses/LICENSE
pyit2fls-0.8.6.dist-info/METADATA
pyit2fls-0.8.6.dist-info/WHEEL
pyit2fls-0.8.6.dist-info/top_level.txt
pyit2fls-0.8.6.dist-info/RECORD
