Metadata-Version: 2.4
Name: pyit2fls
Version: 0.8.6
Summary: Type 1 and Interval Type 2 Fuzzy Logic Systems in Python
Home-page: https://github.com/Haghrah/PyIT2FLS
Author: Amir Arslan Haghrah
Author-email: arslan.haghrah@gmail.com
License: MIT
Requires-Python: >=3.6
License-File: LICENSE
Requires-Dist: numpy
Requires-Dist: scipy
Requires-Dist: matplotlib
Dynamic: author
Dynamic: author-email
Dynamic: description
Dynamic: description-content-type
Dynamic: home-page
Dynamic: license
Dynamic: license-file
Dynamic: requires-dist
Dynamic: requires-python
Dynamic: summary
